setup.py
bin/commandant
commandant/__init__.py
commandant/builtins.py
commandant/commands.py
commandant/controller.py
commandant/entry_point.py
commandant/errors.py
commandant/formatting.py
commandant/help_topics.py
commandant.egg-info/PKG-INFO
commandant.egg-info/SOURCES.txt
commandant.egg-info/dependency_links.txt
commandant.egg-info/not-zip-safe
commandant.egg-info/top_level.txt
commandant/testing/__init__.py
commandant/testing/basic.py
commandant/testing/mocker.py
commandant/testing/resources.py