Metadata-Version: 1.0
Name: commandant
Version: 0.5.0
Summary: Commandant is a toolkit for building command-oriented tools.
Home-page: https://github.com/jkakar/commandant
Author: Jamshed Kakar
Author-email: jkakar@kakar.ca
License: GPL
Platform: UNKNOWN
Classifier: Development Status :: 3 - Alpha
Classifier: Environment :: Console
Classifier: Intended Audience :: Developers
Classifier: Intended Audience :: System Administrators
Classifier: License :: OSI Approved :: GNU General Public License (GPL)
Classifier: Programming Language :: Python
Classifier: Topic :: Utilities
Classifier: Topic :: Software Development :: User Interfaces
